hifilter/__init__.py
hifilter/base.py
hifilter/filters/__init__.py
hifilter/filters/a6_filter.py
hifilter/filters/c1_filter.py
hifilter/filters/f2_filter.py
hifilter/filters/face_filter.py
hifilter/filters/h36_filter.py
hifilter/filters/hb2_filter.py
hifilter/filters/kk2_filter.py
hifilter/filters/m5_filter.py
hifilter/filters/p25_filter.py
hifilter/filters/s40_filter.py
hifilter/filters/tc_filter.py
hifilter/filters/models/AnimeGANv3_Hayao_36.onnx
hifilter/filters/models/AnimeGANv3_PortraitSketch_25.onnx
hifilter/filters/models/AnimeGANv3_Shinkai_40.onnx
hifilter/filters/models/AnimeGANv3_tiny_Cute.onnx
hifilter/filters/models/__init__.py
hifilter/thirdparty/DCT-Net/source/__init__.py
hifilter/thirdparty/DCT-Net/source/cartoonize.py
hifilter/thirdparty/DCT-Net/source/image_flip_agument_parallel.py
hifilter/thirdparty/DCT-Net/source/image_rotation_agument_parallel_flat.py
hifilter/thirdparty/DCT-Net/source/image_scale_agument_parallel_flat.py
hifilter/thirdparty/DCT-Net/source/utils.py
hifilter/thirdparty/DCT-Net/source/facelib/LICENSE
hifilter/thirdparty/DCT-Net/source/facelib/__init__.py
hifilter/thirdparty/DCT-Net/source/facelib/config.py
hifilter/thirdparty/DCT-Net/source/facelib/face_detector.py
hifilter/thirdparty/DCT-Net/source/facelib/face_landmark.py
hifilter/thirdparty/DCT-Net/source/facelib/facer.py
hifilter/thirdparty/DCT-Net/source/facelib/LK/__init__.py
hifilter/thirdparty/DCT-Net/source/facelib/LK/lk.py
hifilter/thirdparty/DCT-Net/source/mtcnn_pytorch/LICENSE
hifilter/thirdparty/DCT-Net/source/mtcnn_pytorch/README.md
hifilter/thirdparty/DCT-Net/source/mtcnn_pytorch/__init__.py
hifilter/thirdparty/DCT-Net/source/mtcnn_pytorch/src/__init__.py
hifilter/thirdparty/DCT-Net/source/mtcnn_pytorch/src/align_trans.py
hifilter/thirdparty/DCT-Net/source/mtcnn_pytorch/src/matlab_cp2tform.py
hifilter/thirdparty/DCT-Net/source/stylegan2/__init__.py
hifilter/thirdparty/DCT-Net/source/stylegan2/dataset.py
hifilter/thirdparty/DCT-Net/source/stylegan2/distributed.py
hifilter-0.2.7.dist-info/METADATA
hifilter-0.2.7.dist-info/WHEEL
hifilter-0.2.7.dist-info/top_level.txt
hifilter-0.2.7.dist-info/RECORD
