Metadata-Version: 2.2
Name: hifilter
Version: 0.2.7
Summary: image filter lib
Home-page: https://github.com/kbrownehs18/hifilter
Author: last911
Author-email: 
Classifier: Programming Language :: Python :: 3
Classifier: License :: OSI Approved :: MIT License
Classifier: Operating System :: OS Independent
Requires-Python: >=3.10
Requires-Dist: pillow
Requires-Dist: opencv-python
Requires-Dist: numpy
Requires-Dist: onnx
Requires-Dist: onnxruntime
Requires-Dist: tensorflow
Requires-Dist: easydict
Requires-Dist: modelscope
Requires-Dist: addict
Dynamic: author
Dynamic: classifier
Dynamic: description
Dynamic: description-content-type
Dynamic: home-page
Dynamic: requires-dist
Dynamic: requires-python
Dynamic: summary
